Hazard_unit.v
module Hazard_unit (
    input [4:0] A1_if,
    input [4:0] A2_if,
    input [4:0] A3_id,
    input [4:0] A1_ex,
    input [4:0] A2_ex,
    input [4:0] A3_m,
    input [4:0] A3_wb,
    input reg_write_m,
    input reg_write_wb,
    input PC_src_if,
    input [6:0] opcode_id,
    output reg [1:0] sel_A_ex,
    output reg [1:0] sel_B_ex,
    output reg en,
    output reg clr
);
    always @(*) begin
        if (A1_ex == A3_m && reg_write_m) sel_A_ex <= 2'd1;
        else if (A1_ex == A3_wb && reg_write_wb) sel_A_ex <= 2'd2;
        else sel_A_ex <= 2'd0;
        
        if (A2_ex == A3_m && reg_write_m) sel_B_ex <= 2'd1;
        else if (A2_ex == A3_wb && reg_write_wb) sel_B_ex <= 2'd2;
        else sel_B_ex <= 2'd0;
    end
    always @(*) begin
        if (opcode_id == 7'h03 && (A1_if == A3_id || A2_if == A3_id)) en <= 1'b0;
        else en <= 1'b1;
    end
    always @(*) begin
        if(PC_src_if) begin
            clr <= 1'b1;
            // en <= 1'b0;
        end
        else begin
            clr <= 1'b0;
            // en <= 1'b1;
        end
    end

endmodule

data_mem.v
module data_mem (
    input clk,
    input rst,
    input WE,
    input [7:0] A,
    input [31:0] WD,
    output reg [31:0] RD
);
    reg [31:0] memory [0:256];
    reg [8:0] i;

    always @(*) begin
        RD <= memory[A];
    end
    always @(posedge clk or negedge rst) begin
        if (!rst) begin
            for (i = 0;i<256;i=i+1) begin
                memory[i] <= 32'd0;
            end
        end
        else if (WE) begin
            memory[A] <= WD;
        end
    end
endmodule

ALU.v
module ALU (
    input [3:0] ALUControl,
    input [31:0] SrcA,
    input [31:0] SrcB,
    output reg zero,
    output reg [31:0] ALUResult
);
    always @(*) begin
        case (ALUControl)
            4'd0: ALUResult <= SrcA & SrcB;
            4'd1: ALUResult <= SrcA | SrcB;
            3'd2: ALUResult <= SrcA + SrcB;
            4'd6: ALUResult <= SrcA - SrcB;
            4'd7: begin
                if (SrcA < SrcB) begin
                    ALUResult <= 32'd1;
                end
                else begin
                    ALUResult <= 32'd0;
                end
            end
            default: ALUResult <= 32'd0;
        endcase
    end
    always @(*) begin
        zero <= (ALUResult == 32'd0);
    end
endmodule

sign_extend.v
module sign_extend (
    input [31:0] instruction,
    input [2:0] imm_sel,
    output reg [31:0] SignImm
);

    localparam  I = 3'd1,
                S = 3'd2,
                B = 3'd3,
                U = 3'd4,
                J = 3'd5;

    always @(*) begin
        case (imm_sel)
            I: SignImm <= {{20{instruction[31]}}, instruction[30:20]};
            S: SignImm <= {{20{instruction[31]}}, instruction[30:25]};
            B: SignImm <= {{19{instruction[31]}}, instruction[7], instruction[30:25], instruction[11:8], 1'b0};
            U: SignImm <= {instruction[31:12], 12'd0};
            J: SignImm <= {{12{instruction[31]}}, instruction[19:12], instruction[20], instruction[30:21], 1'b0};
            default: SignImm <= 31'd0;
        endcase
    end
endmodule

Register_file.v
module Register_file (
    input clk,
    input rst,
    input WE3,
    input [4:0] A1,
    input [4:0] A2,
    input [4:0] A3,
    input [31:0] WD3,
    output reg [31:0] RD1,
    output reg [31:0] RD2
);
    reg [31:0] reg_file [0:31];
    reg [5:0] i;
    always @(*) begin
        RD1 = reg_file[A1];
        RD2 = reg_file[A2];
    end
    initial begin
        reg_file[17] <= 8;
    end
    always @(posedge clk or negedge rst) begin
        if(!rst) begin
            for (i=0;i<32 && i != 17;i=i+1) begin
                reg_file[i] <= 32'd0;
            end
        end
        else if(WE3) begin
            reg_file[A3] <= WD3;
        end
    end
endmodule

Datapath.v
`include "Register_file.v"
`include "sign_extend.v"
`include "data_mem.v"
`include "ALU.v"
`include "Hazard_unit.v"

module Datapath (
    input clk,
    input rst,
    input reg_write_id,
    input mem_write_id,
    input PC_src_if,
    input sel_srcA_id,
    input sel_srcB_id,
    input [1:0] wb_sel_id,
    input [2:0] imm_sel_id,
    output reg comparator_result,
    output reg [31:0] ALUResult_ex,
    output reg [31:0] instruction_id,
    output reg [6:0] opcode_ex,
    input [3:0] ALUControl_id
);

wire clr;

wire [4:0] A1_if, A2_if;
reg [31:0] PC_if;
reg [31:0] instr_mem [0:7];
reg [31:0] PC_mux_0_if, PC_mux_1_if, ALUResult_if, instruction_if;


wire [4:0] A1_id, A2_id, A3_id;
wire [31:0] read_data1_id, read_data2_id, SignImm_id;
reg [4:0] rd_id;
reg [31:0] PC_id, PC_mux_0_id;
reg reg_write_ex, mem_write_ex, sel_srcA_ex, sel_srcB_ex;
reg [1:0] wb_sel_ex;
reg [2:0] imm_sel_ex;
reg [3:0] ALUControl_ex;
reg [4:0] A1_ex, A2_ex, rd_ex;
reg [31:0] new_rd1_data_ex, new_rd2_data_ex, read_data1_ex, read_data2_ex, SignImm_ex;
reg [31:0] PC_ex, PC_mux_0_ex, SrcB_ex, SrcA_ex;


wire [31:0] RD_m;
reg reg_write_m, mem_write_m;
reg [1:0] wb_sel_m;
reg [4:0] rd_m;
reg [31:0] ALUResult_m, PC_mux_0_m, new_rd2_data_m;

reg reg_write_wb;
reg [1:0] wb_sel_wb;
reg [4:0] rd_wb;
reg [31:0] ALUResult_wb, PC_mux_0_wb, RD_wb, write_back_wb;


    initial begin
        instr_mem[0]  <= 32'h00100093; // addi x1,  x0, 1
instr_mem[1]  <= 32'h00100113; // addi x2,  x0, 1

instr_mem[2]  <= 32'h00208263; // beq  x1, x2, +4
instr_mem[3]  <= 32'h06F00513; // addi x10, x0, 111   // MUST be flushed
instr_mem[4]  <= 32'h0DE00513; // addi x10, x0, 222   // MUST be flushed
instr_mem[5]  <= 32'h14D00513; // addi x10, x0, 333   // MUST be flushed

instr_mem[6]  <= 32'h00A00513; // addi x10, x0, 10

        // instr_mem[0] <= 32'h02A00293;
        // instr_mem[1] <= 32'h00552023;
        // instr_mem[2] <= 32'h00052283;
        // instr_mem[3] <= 32'h00A28313;

        // instr_mem[0] <= 32'h00500513;
        // instr_mem[1] <= 32'h00700593;
        // instr_mem[2] <= 32'h00000013;
        // instr_mem[3] <= 32'h00000013;
        // instr_mem[4] <= 32'h00000013;
        // instr_mem[2] <= 32'h00B50633;
        // instr_mem[2] <= 32'h00B50163;
        // instr_mem[3] <= 32'h00A50163;
        // instr_mem[5] <= 32'h06300613;
        // instr_mem[7] <= 32'hFFFFF0EF;
    end

    wire en;

    always @(posedge clk or negedge rst) begin
        if(!rst) begin
            PC_if <= 32'd0;
        end
        else if (!en) PC_if <= PC_if;
        else begin
            if (PC_src_if) PC_if <= PC_mux_1_if;
            else PC_if <= PC_mux_0_if;
            
        end
    end


    always @(*) begin
        PC_mux_0_if <= PC_if + 1;
        PC_mux_1_if <= ALUResult_ex;
        instruction_if <= instr_mem[PC_if];
    end


    assign A1_if = instruction_if[19:15];
    assign A2_if = instruction_if[24:20];

    assign A1_id = instruction_id[19:15];
    assign A2_id = instruction_id[24:20];
    assign A3_id = instruction_id[11:7];

    wire [1:0] sel_A_ex, sel_B_ex;

    always @(*) begin
        // comparator_result <= (new_rd1_data_ex == new_rd2_data_ex);
        if (new_rd1_data_ex == new_rd2_data_ex) comparator_result <= 1'b1;
        else comparator_result <= 1'b0;
    end

    always @(*) begin
        if (sel_A_ex == 2'd1) new_rd1_data_ex <= ALUResult_m;
        else if(sel_A_ex == 2'd2) new_rd1_data_ex <= write_back_wb;
        else new_rd1_data_ex <= read_data1_ex;
    end

    always @(*) begin
        if (sel_B_ex == 2'd1) new_rd2_data_ex <= ALUResult_m;
        else if(sel_B_ex == 2'd2) new_rd2_data_ex <= write_back_wb;
        else new_rd2_data_ex <= read_data2_ex;
    end

    always @(*) begin
        if (sel_srcA_ex) SrcA_ex = new_rd1_data_ex;
        else SrcA_ex = PC_ex;
    end

    always @(*) begin
        if (sel_srcB_ex) SrcB_ex = new_rd2_data_ex;
        else SrcB_ex = SignImm_ex;
    end

    always @(*) begin
        if (wb_sel_wb == 2'd0) write_back_wb = RD_wb;
        else if (wb_sel_wb == 2'd1) write_back_wb = ALUResult_wb;
        else write_back_wb = PC_mux_0_wb;
    end


// IF -> ID

    always @(posedge clk or negedge rst) begin
        if(!rst || clr) begin
            instruction_id <= 32'd0;
            PC_id <= 32'd0;
            PC_mux_0_id <= 32'd0;
        end
        else if (!en) begin
            instruction_id <= 32'h00000013;
        end
        else begin
            instruction_id <= instruction_if;
            PC_mux_0_id <= PC_mux_0_if;
            PC_id <= PC_if;
        end
    end

// ID -> Ex

    always @(posedge clk or negedge rst) begin
        if(!rst || clr) begin
            read_data1_ex <= 32'd0;
            read_data2_ex <= 32'd0;
            rd_ex <= 5'd0;
            SignImm_ex <= 32'd0;
            PC_ex <= 32'd0;
            sel_srcA_ex <= 1'b0;
            sel_srcB_ex <= 1'b0;
            PC_mux_0_ex <= 32'd0;
            reg_write_ex <= 1'b0;
            mem_write_ex <= 1'b0;
            wb_sel_ex <= 2'd0;
            imm_sel_ex <= 3'd0;
            ALUControl_ex <= 4'd0;
            A1_ex <= 5'd0;
            A2_ex <= 5'd0;
            opcode_ex <= 7'd0;
        end
        else begin
            read_data1_ex <= read_data1_id;
            read_data2_ex <= read_data2_id;
            rd_ex <= A3_id;
            SignImm_ex <= SignImm_id;
            PC_ex <= PC_id;
            sel_srcA_ex <= sel_srcA_id;
            sel_srcB_ex <= sel_srcB_id;
            PC_mux_0_ex <= PC_mux_0_id;
            reg_write_ex <= reg_write_id;
            mem_write_ex <= mem_write_id;
            wb_sel_ex <= wb_sel_id;
            imm_sel_ex <= imm_sel_id;
            ALUControl_ex <= ALUControl_id;
            A1_ex <= A1_id;
            A2_ex <= A2_id;
            opcode_ex <= opcode_id;
        end
    end

// Ex t0 M

    always @(posedge clk or negedge rst) begin
        if (!rst) begin
            ALUResult_m <= 32'd0;
            new_rd2_data_m <= 32'd0;
            rd_m <= 5'd0;
            reg_write_m <= 1'b0;
            PC_mux_0_m <= 32'd0;
            mem_write_m <= 1'b0;
            wb_sel_m <= 2'd0;
        end
        else begin
            ALUResult_m <= ALUResult_ex;
            new_rd2_data_m <= new_rd2_data_ex;
            rd_m <= rd_ex;
            PC_mux_0_m <= PC_mux_0_ex;
            reg_write_m <= reg_write_ex;
            mem_write_m <= mem_write_ex;
            wb_sel_m <= wb_sel_ex;
        end
    end

// M to Wb

    always @(posedge clk or negedge rst) begin
        if (!rst) begin
            ALUResult_wb <= 32'd0;
            RD_wb <= 32'd0;
            rd_wb <= 5'd0;
            PC_mux_0_wb <= 32'd0;
            reg_write_wb <= 1'b0;
            wb_sel_wb <= 2'd0;
        end
        else begin
            ALUResult_wb <= ALUResult_m;
            RD_wb <= RD_m;
            rd_wb <= rd_m;
            PC_mux_0_wb <= PC_mux_0_m;
            reg_write_wb <= reg_write_m;
            wb_sel_wb <= wb_sel_m;
        end
    end


    Register_file r1 (
        .clk(clk),
        .rst(rst),
        .A1(A1_id),
        .A2(A2_id),
        .A3(rd_wb),
        .WE3(reg_write_wb),
        .WD3(write_back_wb),
        .RD1(read_data1_id),
        .RD2(read_data2_id)
    );
    wire [31:0] instruction_id_1;
    assign instruction_id_1 = instruction_id;

    sign_extend s1 (
        .instruction(instruction_id_1),
        .imm_sel(imm_sel_id),
        .SignImm(SignImm_id)
    );
    wire [31:0] ALUResult_ex_1;
    assign ALUResult_ex_1 = ALUResult_ex;
    ALU a1 (
        .ALUControl(ALUControl_ex),
        .SrcA(SrcA_ex),
        .SrcB(SrcB_ex),
        .ALUResult(ALUResult_ex_1)
    );

    data_mem dm1 (
        .clk(clk),
        .rst(rst),
        .WE(mem_write_m),
        .A(ALUResult_m[7:0]),
        .RD(RD_m),
        .WD(new_rd2_data_m)
    );
    
    wire [6:0] opcode_id;
    assign opcode_id = instruction_id[6:0];

    Hazard_unit h1 (
        .A1_if(A1_if),
        .A2_if(A2_if),
        .A3_id(A3_id),
        .A1_ex(A1_ex),
        .A2_ex(A2_ex),
        .A3_m(rd_m),
        .A3_wb(rd_wb),
        .PC_src_if(PC_src_if),
        .clr(clr),
        .reg_write_m(reg_write_m),
        .reg_write_wb(reg_write_wb),
        .sel_A_ex(sel_A_ex),
        .sel_B_ex(sel_B_ex),
        .en(en),
        .opcode_id(opcode_id)
    );
    
endmodule

Control_unit.v
module Control_unit (
    input clk,
    input rst,
    input [31:0] instruction,
    input comparator_result,
    input [6:0] opcode_ex,
    output reg reg_write,
    output reg mem_write,
    output reg PC_src_if,
    output reg sel_srcA_id,
    output reg sel_srcB_id,
    output reg [1:0] wb_sel,
    output reg [3:0] ALUControl, 
    output reg [2:0] imm_sel
);

    localparam  R = 7'H33,
                I = 7'H13,
                L = 7'H03,
                S = 7'H23,
                B = 7'H63,
                J = 7'H6F,
                U = 7'H37;

    reg [1:0] ALUop;

    wire [6:0] instr;
    assign instr = instruction[6:0];
    always @(*) begin
        case (instr)
            R: begin
                reg_write <= 1'b1;
                mem_write <= 1'b0;
                imm_sel <= 2'd0;
                wb_sel <= 2'd1;
                ALUop <= 2'd2;
                sel_srcA_id <= 1'b1;
                sel_srcB_id <= 1'b1;
            end
            I: begin
                reg_write <= 1'b1;
                mem_write <= 1'b0;
                imm_sel <= 3'd1;
                wb_sel <= 2'd1;
                ALUop <= 2'd2;
                sel_srcA_id <= 1'b1;
                sel_srcB_id <= 1'b0;
            end
            L: begin
                reg_write <= 1'b1;
                mem_write <= 1'b0;
                imm_sel <= 3'd1;
                wb_sel <= 2'd0;
                ALUop <= 2'd0;
                sel_srcA_id <= 1'b1;
                sel_srcB_id <= 1'b0;
            end
            S: begin
                reg_write <= 1'b0;
                mem_write <= 1'b1;
                imm_sel <= 3'd2;
                ALUop <= 2'd0;
                sel_srcA_id <= 1'b1;
                sel_srcB_id <= 1'b0;

            end
            B: begin
                reg_write <= 1'b0;
                mem_write <= 1'b0;
                imm_sel <= 3'd3;
                ALUop <= 2'd0;
                sel_srcA_id <= 1'b0;
                sel_srcB_id <= 1'b0;
            end
            U: begin
                imm_sel <= 3'd4;
            end
            J: begin
                reg_write <= 1'b1;
                mem_write <= 1'b0;
                imm_sel <= 3'd5;
                wb_sel <= 2'd2;
                ALUop <= 2'd0;
                sel_srcA_id <= 1'b0;
                sel_srcB_id <= 1'b0;
            end
            default: begin
                
            end
        endcase
    end

    always @(*) begin
        case (ALUop)
            2'd0: ALUControl <= 4'd2;
            2'd1: ALUControl <= 4'd6;
            2'd2: begin
                case (instruction[14:12])
                    3'd0: begin
                        if(instruction[31:25] == 7'd0) ALUControl <= 4'd2;
                        else if (instruction[31:25] == 7'd32) ALUControl <= 4'd6;
                        else ALUControl <= 4'd2;
                    end
                    3'd6: ALUControl <= 4'd1;
                    3'd7: ALUControl <= 4'd0;
                endcase
            end
            default: ALUControl <= 4'd15;
        endcase
    end

    always @(*) begin
        case (opcode_ex)
            B: begin
                if (comparator_result) PC_src_if <= 1'b1;
                else PC_src_if <= 1'b0;
            end
            J: begin
                PC_src_if <= 1'b1;
            end
            default: PC_src_if <= 1'b0;
        endcase
    end

endmodule

Processor.v
`include "Control_unit.v"
`include "Datapath.v"
`timescale 1ps/1ps
module Processor (
    // input clk,
    // input rst
);

    wire reg_write, mem_write, PC_src_if, sel_srcA_id, sel_srcB_id, comparator_result;
    wire [1:0] wb_sel;
    wire [2:0] imm_sel;
    reg clk, rst;
    wire [3:0] ALUControl;
    wire [31:0] instruction;
    wire [6:0] opcode_ex;

    Control_unit cu1 (
        .clk(clk),
        .rst(rst),
        .instruction(instruction),
        .wb_sel(wb_sel),
        .imm_sel(imm_sel),
        .comparator_result(comparator_result),
        .reg_write(reg_write),
        .mem_write(mem_write),
        .ALUControl(ALUControl),
        .opcode_ex(opcode_ex),
        .PC_src_if(PC_src_if),
        .sel_srcA_id(sel_srcA_id),
        .sel_srcB_id(sel_srcB_id)
    );
    Datapath dp1(
        .clk(clk),
        .rst(rst),
        .instruction_id(instruction),
        .wb_sel_id(wb_sel),
        .imm_sel_id(imm_sel),
        .comparator_result(comparator_result),
        .reg_write_id(reg_write),
        .mem_write_id(mem_write),
        .ALUControl_id(ALUControl),
        .opcode_ex(opcode_ex),
        .PC_src_if(PC_src_if),
        .sel_srcA_id(sel_srcA_id),
        .sel_srcB_id(sel_srcB_id)
    );
    initial begin
        $dumpfile("Processor.vcd");
        $dumpvars(0,Processor);
        #200 $finish;
    end
    initial begin
        rst = 0;
        #10 rst = 1'b1;
    end
    initial begin
        clk = 0;
        forever begin
            #5 clk = ~ clk;
        end
    end



endmodule

Processor.vcd
$date
	Tue Oct  6 14:45:21 2026
$end
$version
	Icarus Verilog
$end
$timescale
	1ps
$end
$scope module Processor $end
$var wire 2 ! wb_sel [1:0] $end
$var wire 1 " sel_srcB_id $end
$var wire 1 # sel_srcA_id $end
$var wire 1 $ reg_write $end
$var wire 7 % opcode_ex [6:0] $end
$var wire 1 & mem_write $end
$var wire 32 ' instruction [31:0] $end
$var wire 3 ( imm_sel [2:0] $end
$var wire 1 ) comparator_result $end
$var wire 1 * PC_src_if $end
$var wire 4 + ALUControl [3:0] $end
$var reg 1 , clk $end
$var reg 1 - rst $end
$scope module cu1 $end
$var wire 1 , clk $end
$var wire 1 - rst $end
$var wire 7 . opcode_ex [6:0] $end
$var wire 32 / instruction [31:0] $end
$var wire 7 0 instr [6:0] $end
$var wire 1 ) comparator_result $end
$var parameter 7 1 B $end
$var parameter 7 2 I $end
$var parameter 7 3 J $end
$var parameter 7 4 L $end
$var parameter 7 5 R $end
$var parameter 7 6 S $end
$var parameter 7 7 U $end
$var reg 4 8 ALUControl [3:0] $end
$var reg 2 9 ALUop [1:0] $end
$var reg 1 * PC_src_if $end
$var reg 3 : imm_sel [2:0] $end
$var reg 1 & mem_write $end
$var reg 1 $ reg_write $end
$var reg 1 # sel_srcA_id $end
$var reg 1 " sel_srcB_id $end
$var reg 2 ; wb_sel [1:0] $end
$upscope $end
$scope module dp1 $end
$var wire 4 < ALUControl_id [3:0] $end
$var wire 32 = ALUResult_ex_1 [31:0] $end
$var wire 1 * PC_src_if $end
$var wire 1 , clk $end
$var wire 3 > imm_sel_id [2:0] $end
$var wire 32 ? instruction_id_1 [31:0] $end
$var wire 1 & mem_write_id $end
$var wire 1 $ reg_write_id $end
$var wire 1 - rst $end
$var wire 1 # sel_srcA_id $end
$var wire 1 " sel_srcB_id $end
$var wire 2 @ wb_sel_id [1:0] $end
$var wire 2 A sel_B_ex [1:0] $end
$var wire 2 B sel_A_ex [1:0] $end
$var wire 32 C read_data2_id [31:0] $end
$var wire 32 D read_data1_id [31:0] $end
$var wire 7 E opcode_id [6:0] $end
$var wire 1 F en $end
$var wire 1 G clr $end
$var wire 32 H SignImm_id [31:0] $end
$var wire 32 I RD_m [31:0] $end
$var wire 5 J A3_id [4:0] $end
$var wire 5 K A2_if [4:0] $end
$var wire 5 L A2_id [4:0] $end
$var wire 5 M A1_if [4:0] $end
$var wire 5 N A1_id [4:0] $end
$var reg 5 O A1_ex [4:0] $end
$var reg 5 P A2_ex [4:0] $end
$var reg 4 Q ALUControl_ex [3:0] $end
$var reg 32 R ALUResult_ex [31:0] $end
$var reg 32 S ALUResult_m [31:0] $end
$var reg 32 T ALUResult_wb [31:0] $end
$var reg 32 U PC_ex [31:0] $end
$var reg 32 V PC_id [31:0] $end
$var reg 32 W PC_if [31:0] $end
$var reg 32 X PC_mux_0_ex [31:0] $end
$var reg 32 Y PC_mux_0_id [31:0] $end
$var reg 32 Z PC_mux_0_if [31:0] $end
$var reg 32 [ PC_mux_0_m [31:0] $end
$var reg 32 \ PC_mux_0_wb [31:0] $end
$var reg 32 ] PC_mux_1_if [31:0] $end
$var reg 32 ^ RD_wb [31:0] $end
$var reg 32 _ SignImm_ex [31:0] $end
$var reg 32 ` SrcA_ex [31:0] $end
$var reg 32 a SrcB_ex [31:0] $end
$var reg 1 ) comparator_result $end
$var reg 3 b imm_sel_ex [2:0] $end
$var reg 32 c instruction_id [31:0] $end
$var reg 32 d instruction_if [31:0] $end
$var reg 1 e mem_write_ex $end
$var reg 1 f mem_write_m $end
$var reg 32 g new_rd1_data_ex [31:0] $end
$var reg 32 h new_rd2_data_ex [31:0] $end
$var reg 32 i new_rd2_data_m [31:0] $end
$var reg 7 j opcode_ex [6:0] $end
$var reg 5 k rd_ex [4:0] $end
$var reg 5 l rd_m [4:0] $end
$var reg 5 m rd_wb [4:0] $end
$var reg 32 n read_data1_ex [31:0] $end
$var reg 32 o read_data2_ex [31:0] $end
$var reg 1 p reg_write_ex $end
$var reg 1 q reg_write_m $end
$var reg 1 r reg_write_wb $end
$var reg 1 s sel_srcA_ex $end
$var reg 1 t sel_srcB_ex $end
$var reg 2 u wb_sel_ex [1:0] $end
$var reg 2 v wb_sel_m [1:0] $end
$var reg 2 w wb_sel_wb [1:0] $end
$var reg 32 x write_back_wb [31:0] $end
$scope module a1 $end
$var wire 4 y ALUControl [3:0] $end
$var wire 32 z SrcA [31:0] $end
$var wire 32 { SrcB [31:0] $end
$var reg 32 | ALUResult [31:0] $end
$var reg 1 } zero $end
$upscope $end
$scope module dm1 $end
$var wire 8 ~ A [7:0] $end
$var wire 32 !" WD [31:0] $end
$var wire 1 f WE $end
$var wire 1 , clk $end
$var wire 1 - rst $end
$var reg 32 "" RD [31:0] $end
$var reg 9 #" i [8:0] $end
$upscope $end
$scope module h1 $end
$var wire 5 $" A1_ex [4:0] $end
$var wire 5 %" A1_if [4:0] $end
$var wire 5 &" A2_ex [4:0] $end
$var wire 5 '" A2_if [4:0] $end
$var wire 5 (" A3_id [4:0] $end
$var wire 5 )" A3_m [4:0] $end
$var wire 5 *" A3_wb [4:0] $end
$var wire 1 * PC_src_if $end
$var wire 7 +" opcode_id [6:0] $end
$var wire 1 q reg_write_m $end
$var wire 1 r reg_write_wb $end
$var reg 1 G clr $end
$var reg 1 F en $end
$var reg 2 ," sel_A_ex [1:0] $end
$var reg 2 -" sel_B_ex [1:0] $end
$upscope $end
$scope module r1 $end
$var wire 5 ." A1 [4:0] $end
$var wire 5 /" A2 [4:0] $end
$var wire 5 0" A3 [4:0] $end
$var wire 32 1" WD3 [31:0] $end
$var wire 1 r WE3 $end
$var wire 1 , clk $end
$var wire 1 - rst $end
$var reg 32 2" RD1 [31:0] $end
$var reg 32 3" RD2 [31:0] $end
$var reg 6 4" i [5:0] $end
$upscope $end
$scope module s1 $end
$var wire 3 5" imm_sel [2:0] $end
$var wire 32 6" instruction [31:0] $end
$var parameter 3 7" B $end
$var parameter 3 8" I $end
$var parameter 3 9" J $end
$var parameter 3 :" S $end
$var parameter 3 ;" U $end
$var reg 32 <" SignImm [31:0] $end
$upscope $end
$upscope $end
$upscope $end
$enddefinitions $end
$comment Show the parameter values. $end
$dumpall
b100 ;"
b10 :"
b101 9"
b1 8"
b11 7"
b110111 7
b100011 6
b110011 5
b11 4
b1101111 3
b10011 2
b1100011 1
$end
#0
$dumpvars
b0 <"
b0 6"
bx 5"
b10001 4"
b0 3"
b0 2"
b0 1"
b0 0"
b0 /"
b0 ."
b0 -"
b0 ,"
b0 +"
b0 *"
b0 )"
b0 ("
b1 '"
b0 &"
b0 %"
b0 $"
b100000000 #"
b0 ""
b0 !"
b0 ~
1}
b0 |
b0 {
b0 z
b0 y
b0 x
b0 w
b0 v
b0 u
0t
0s
0r
0q
0p
b0 o
b0 n
b0 m
b0 l
b0 k
b0 j
b0 i
b0 h
b0 g
0f
0e
b100000000000010010011 d
b0 c
b0 b
b0 a
b0 `
b0 _
b0 ^
bx ]
b0 \
b0 [
b1 Z
b0 Y
b0 X
b0 W
b0 V
b0 U
b0 T
b0 S
bx R
b0 Q
b0 P
b0 O
b0 N
b0 M
b0 L
b1 K
b0 J
b0 I
b0 H
0G
1F
b0 E
b0 D
b0 C
b0 B
b0 A
bx @
b0 ?
bx >
bx =
b1111 <
bx ;
bx :
bx 9
b1111 8
b0 0
b0 /
b0 .
0-
0,
b1111 +
0*
1)
bx (
b0 '
x&
b0 %
x$
x#
x"
bx !
$end
#5
b100000000 #"
b10001 4"
1,
#10
0,
1-
#15
b10 +
b10 8
b10 <
b1 H
b1 <"
0"
1#
b10 9
b1 !
b1 ;
b1 @
b1 (
b1 :
b1 >
b1 5"
0&
1$
bx I
bx ""
b100000000000100010011 d
b10 Z
b1 L
b1 /"
b1 J
b1 ("
b10011 E
b10011 +"
b10011 0
bx ~
b1 W
b1 Y
b100000000000010010011 ?
b100000000000010010011 6"
b100000000000010010011 '
b100000000000010010011 /
b100000000000010010011 c
b1111 Q
b1111 y
bx b
bx u
xe
xp
xt
xs
bx S
1,
#20
0,
#25
0}
b1 M
b1 %"
b10 K
b10 '"
b1 |
b1000001000001001100011 d
b11 Z
bx x
bx 1"
b1 a
b1 {
b10 J
b10 ("
bx ^
bx T
bx v
xf
xq
b10011 %
b10011 .
b10011 j
b1 P
b1 &"
b10 Q
b10 y
b1 b
b1 u
0e
1p
b1 X
0t
1s
b1 _
b1 k
b1 V
b10 Y
b100000000000100010011 ?
b100000000000100010011 6"
b100000000000100010011 '
b100000000000100010011 /
b100000000000100010011 c
b10 W
1,
#30
0,
#35
0)
bx h
b0 M
b0 %"
b1111 K
b1111 '"
0#
b0 9
b11 (
b11 :
b11 >
b11 5"
0$
b110111100000000010100010011 d
b100 Z
b100 H
b100 <"
b1 A
b1 -"
b1 N
b1 ."
b10 L
b10 /"
b100 J
b100 ("
b1100011 E
b1100011 +"
b1100011 0
b0 x
b0 1"
b11 W
b10 V
b11 Y
b1000001000001001100011 ?
b1000001000001001100011 6"
b1000001000001001100011 '
b1000001000001001100011 /
b1000001000001001100011 c
b10 X
b1 U
b10 k
b1 v
0f
1q
b1 [
b1 l
b1 )"
bx w
xr
1,
#40
0,
#45
bx g
b11110 K
b11110 '"
b110 |
1#
b10 9
b1 (
b1 :
b1 >
b1 5"
1$
b10 B
b10 ,"
b1101111 H
b1101111 <"
b1101111000000000010100010011 d
b101 Z
bx x
bx 1"
b10 `
b10 z
b100 a
b100 {
b0 N
b0 ."
b1111 L
b1111 /"
b1010 J
b1010 ("
b10011 E
b10011 +"
b10011 0
b1 w
1r
b1 \
b1 m
b1 *"
b1 0"
b10 [
b10 l
b10 )"
bx i
bx !"
b1100011 %
b1100011 .
b1100011 j
b10 P
b10 &"
b1 O
b1 $"
b11 b
0p
b11 X
0s
b10 U
b100 _
b100 k
b11 V
b100 Y
b110111100000000010100010011 ?
b110111100000000010100010011 6"
b110111100000000010100010011 '
b110111100000000010100010011 /
b110111100000000010100010011 c
b100 W
1,
#50
0,
#55
1)
0}
b0 h
b0 g
b1101 K
b1101 '"
b1101111 |
b10100110100000000010100010011 d
b110 Z
b11011110 H
b11011110 <"
b0 A
b0 -"
b0 B
b0 ,"
bx C
bx 3"
b11110 L
b11110 /"
b0 `
b0 z
b1101111 a
b1101111 {
b101 W
b100 V
b101 Y
b1101111000000000010100010011 ?
b1101111000000000010100010011 6"
b1101111000000000010100010011 '
b1101111000000000010100010011 /
b1101111000000000010100010011 c
b10011 %
b10011 .
b10011 j
b1111 P
b1111 &"
b0 O
b0 $"
b1 b
1p
b100 X
1s
b11 U
b1101111 _
b1010 k
0q
b11 [
b100 l
b100 )"
b10 \
b10 m
b10 *"
b10 0"
1,
#60
0,
#65
0)
b1010 K
b1010 '"
b11011110 |
bx h
b101001101 H
b101001101 <"
b101000000000010100010011 d
b111 Z
b0 C
b0 3"
b11011110 a
b11011110 {
b1101 L
b1101 /"
0r
b11 \
b100 m
b100 *"
b100 0"
1q
b100 [
b1010 l
b1010 )"
b0 i
b0 !"
b11110 P
b11110 &"
b101 X
b100 U
b11011110 _
bx o
b101 V
b110 Y
b10100110100000000010100010011 ?
b10100110100000000010100010011 6"
b10100110100000000010100010011 '
b10100110100000000010100010011 /
b10100110100000000010100010011 c
b110 W
1,
#70
0,
#75
1)
bx M
bx %"
bx K
bx '"
b101001101 |
bx d
b1000 Z
b1010 H
b1010 <"
b0 h
b1010 L
b1010 /"
b101001101 a
b101001101 {
b111 W
b110 V
b111 Y
b101000000000010100010011 ?
b101000000000010100010011 6"
b101000000000010100010011 '
b101000000000010100010011 /
b101000000000010100010011 c
b1101 P
b1101 &"
b110 X
b101 U
b101001101 _
b0 o
b101 [
bx i
bx !"
1r
b100 \
b1010 m
b1010 *"
b1010 0"
1,
#80
0,
#85
0)
bx h
b1010 |
b1 A
b1 -"
b0xxxxxxxxxxxxxxxxxxxxxxxxxxxxxxx H
b0xxxxxxxxxxxxxxxxxxxxxxxxxxxxxxx <"
b1001 Z
bx D
bx 2"
b1010 a
b1010 {
bx N
bx ."
bx L
bx /"
bx J
bx ("
bx E
bx +"
bx 0
bx C
bx 3"
b101 \
b110 [
b0 i
b0 !"
b1010 P
b1010 &"
b111 X
b110 U
b1010 _
b111 V
b1000 Y
bx ?
bx 6"
bx '
bx /
bx c
b1000 W
1,
#90
0,
#95
x}
bx `
bx z
bx |
b1010 Z
b0 A
b0 -"
bx g
b0xxxxxxxxxxxxxxxxxxxxxxxxxxxxxxx a
b0xxxxxxxxxxxxxxxxxxxxxxxxxxxxxxx {
b1001 W
b1000 V
b1001 Y
bx %
bx .
bx j
bx P
bx &"
bx O
bx $"
b1000 X
b111 U
b0xxxxxxxxxxxxxxxxxxxxxxxxxxxxxxx _
bx k
bx o
bx n
b111 [
bx i
bx !"
b110 \
1,
#100
0,
#105
b1011 Z
b111 \
b1000 [
bx l
bx )"
b1001 X
b1000 U
b1001 V
b1010 Y
b1010 W
1,
#110
0,
#115
b1100 Z
b1011 W
b1010 V
b1011 Y
b1010 X
b1001 U
b1001 [
b1000 \
bx m
bx *"
bx 0"
1,
#120
0,
#125
b1101 Z
b1001 \
b1010 [
b1011 X
b1010 U
b1011 V
b1100 Y
b1100 W
1,
#130
0,
